seaman/__init__.py
seaman/cache/CacheUtil.py
seaman/cache/__init__.py
seaman/core/DateUtil.py
seaman/core/FileUtil.py
seaman/core/HashUtil.py
seaman/core/HexUtil.py
seaman/core/IdUtil.py
seaman/core/JsonUtil.py
seaman/core/OsUtil.py
seaman/core/StrUtil.py
seaman/core/UrlUtil.py
seaman/core/Validator.py
seaman/core/__init__.py
seaman/extra/ExcelUtil.py
seaman/extra/__init__.py
seaman/http/HttpUtil.py
seaman/http/__init__.py
test/__init__.py
seaman-1.0.0.post3.dist-info/LICENSE
seaman-1.0.0.post3.dist-info/METADATA
seaman-1.0.0.post3.dist-info/WHEEL
seaman-1.0.0.post3.dist-info/top_level.txt
seaman-1.0.0.post3.dist-info/RECORD
