Metadata-Version: 2.1
Name: seaman
Version: 1.0.0.post3
Summary: a python tool like java hutool
Home-page: https://gitee.com/Kindear/seaman
Author: kindear
Author-email: kindear@foxmail.com
License: MIT
Classifier: License :: OSI Approved :: MIT License
Classifier: Programming Language :: Python
Classifier: Programming Language :: Python :: 3
Classifier: Programming Language :: Python :: 3.7
Classifier: Programming Language :: Python :: Implementation :: CPython
Classifier: Programming Language :: Python :: Implementation :: PyPy
Requires-Python: >=3.7.0
License-File: LICENSE
